Workbook

Sheet BASE OFICIAL
C2: PLANILHA DE APURAÇÃO DE CUSTOS | E2: OBRA | I2: APURAÇÃO | J2: CLIENTE: | L2: OBRA FICTÍCIA
E3: FICTÍCIA | G3: Nº | I3: 28
F6: VALOR UNITÁRIO | I6: REALIZADO MÃO DE OBRA | L6: REALIZADO MATERIAIS
B7: ITEM | C7: DESCRICAO | D7: UND | E7: QTD | F7: MATERIAIS | G7: MÃO DE OBRA | H7: ORÇAMENTO UNIT | I7: ORÇADO | J7: REALIZADO | K7: % | L7: ORÇADO | N7: % | O7: ORÇAMENTO TOTAL | P7: SALDO | Q7: PREVISÃO | R7: % BUDGET
B8: ORÇAMENTO TOTAL | E8: =E9+E19+E34+E41+E52+E59+E65+E74+E77+E81+E85+E90+E94+E108+E121 -> 27259.586 | F8: =F9+F19+F34+F41+F52+F59+F65+F74+F77+F81+F85+F90+F94+F108+F121 -> 15926.18 | G8: =G9+G19+G34+G41+G52+G59+G65+G74+G77+G81+G85+G90+G94+G108+G121 -> 11657.47 | H8: =H9+H19+H34+H41+H52+H59+H65+H74+H77+H81+H85+H90+H94+H108+H121 -> 579375.72 | I8: =I9+I19+I34+I41+I52+I59+I65+I74+I77+I81+I85+I90+I94+I108+I121+I125 -> 1125756.3 | L8: =L9+L19+L34+L41+L52+L59+L65+L74+L77+L81+L85+L90+L94+L108+L121+L125 -> 1090023.3 | O8: =L8+I8 -> 2215779.7 | Q8: =Q9+Q19+Q34+Q41+Q52+Q59+Q65+Q74+Q77+Q81+Q85+Q90+Q94+Q108+Q121+Q125 -> 2215779.7 | R8: =IF(O8=0,0,+Q8/O8-1) -> 0
B9: 1 | C9: SERVIÇOS PRELIMINARES | E9: =SUM(E10:E17) -> 1681.4 | F9: =SUM(F10:F18) -> 7357.18 | G9: =SUM(G10:G18) -> 6798.47 | H9: =SUM(H10:H18) -> 58643.174 | I9: =SUM(I10:I18) -> 35228.244 | K9: =SUM(K10:K17)/COUNT(K10:K17) -> #DIV/0! | L9: =SUM(L10:L18) -> 58643.174 | N9: =SUM(N10:N17)/COUNT(N10:N17) -> #DIV/0! | O9: =SUM(O10:O18) -> 93871.418 | Q9: =SUM(Q10:Q18) -> 93871.418 | R9: =IF(O9=0,0,+Q9/O9-1) -> 0 | S9: 1
A10: =$B$9&"."&B10 -> 1.1.1 | B10: 1.1 | C10: PLACA DE OBRA EM CHAPA DE ACO GALVANIZADO | D10: m2 | E10: 4 | F10: 269.46 | G10: 42.15 | H10: =E10*F10 -> 1077.84 | I10: =E10*G10 -> 168.6 | L10: =E10*F10 -> 1077.84 | O10: =L10+I10 -> 1246.44 | Q10: =IF(K10="",I10,J10/K10)+IF(N10="",L10,M10/N10) -> 1246.44 | R10: =IF(O10=0,0,+Q10/O10-1) -> 0 | S10: 2
A11: =$B$9&"."&B11 -> 1.1.2 | B11: 1.2 | C11: BARRACAO DE OBRA ALOJAMENTO/ESCRITORIO | D11: m2 | E11: 29 | F11: 245.65 | G11: 190.09 | H11: =E11*F11 -> 7123.85 | I11: =E11*G11 -> 5512.61 | L11: =E11*F11 -> 7123.85 | O11: =L11+I11 -> 12636.46 | Q11: =IF(K11="",I11,J11/K11)+IF(N11="",L11,M11/N11) -> 12636.46 | R11: =IF(O11=0,0,+Q11/O11-1) -> 0 | S11: 3
A12: =$B$9&"."&B12 -> 1.1.3 | B12: 1.3 | C12: EQUIPAMENTOS PARA BARRACÃO | D12: vb | E12: 1 | F12: 2856 | G12: 0 | H12: =E12*F12 -> 2856 | I12: =E12*G12 -> 0 | L12: =E12*F12 -> 2856 | O12: =L12+I12 -> 2856 | Q12: =IF(K12="",I12,J12/K12)+IF(N12="",L12,M12/N12) -> 2856 | R12: =IF(O12=0,0,+Q12/O12-1) -> 0 | S12: 4
A13: =$B$9&"."&B13 -> 1.1.4 | B13: 1.4 | C13: LIMPEZA MANUAL DE VEGETAÇÃO EM TERRENO | D13: m2 | E13: 715 | F13: 1.26 | G13: 2.15 | H13: =E13*F13 -> 900.9 | I13: =E13*G13 -> 1537.25 | L13: =E13*F13 -> 900.9 | O13: =L13+I13 -> 2438.15 | Q13: =IF(K13="",I13,J13/K13)+IF(N13="",L13,M13/N13) -> 2438.15 | R13: =IF(O13=0,0,+Q13/O13-1) -> 0 | S13: 5
A14: =$B$9&"."&B14 -> 1.1.5 | B14: 1.5 | C14: LOCACAO CONVENCIONAL DE OBRA (GABARITO) | D14: ml | E14: 161.4 | F14: 28.56 | G14: 25.56 | H14: =E14*F14 -> 4609.584 | I14: =E14*G14 -> 4125.384 | L14: =E14*F14 -> 4609.584 | O14: =L14+I14 -> 8734.968 | Q14: =IF(K14="",I14,J14/K14)+IF(N14="",L14,M14/N14) -> 8734.968 | R14: =IF(O14=0,0,+Q14/O14-1) -> 0 | S14: 6
A15: =$B$9&"."&B15 -> 1.1.6 | B15: 1.6 | C15: MOVIMENTAÇÃO DE TERRA | D15: m3 | E15: 550 | F15: 45 | G15: 27 | H15: =E15*F15 -> 24750 | I15: =E15*G15 -> 14850 | L15: =E15*F15 -> 24750 | O15: =L15+I15 -> 39600 | Q15: =IF(K15="",I15,J15/K15)+IF(N15="",L15,M15/N15) -> 39600 | R15: =IF(O15=0,0,+Q15/O15-1) -> 0 | S15: 7
A16: =$B$9&"."&B16 -> 1.1.7 | B16: 1.7 | C16: TAPUME COM TELHA METÁLICA | D16: m2 | E16: 220 | F16: 61.25 | G16: 11.52 | H16: =E16*F16 -> 13475 | I16: =E16*G16 -> 2534.4 | L16: =E16*F16 -> 13475 | O16: =L16+I16 -> 16009.4 | Q16: =IF(K16="",I16,J16/K16)+IF(N16="",L16,M16/N16) -> 16009.4 | R16: =IF(O16=0,0,+Q16/O16-1) -> 0 | S16: 8
A17: =$B$9&"."&B17 -> 1.1.8 | B17: 1.8 | C17: INSTALAÇÃO PROVISÓRIA ELÉTRICA E HIDRÁULICA | D17: vb | E17: 1 | F17: 3850 | G17: 2400 | H17: =E17*F17 -> 3850 | I17: =E17*G17 -> 2400 | L17: =E17*F17 -> 3850 | O17: =L17+I17 -> 6250 | Q17: =IF(K17="",I17,J17/K17)+IF(N17="",L17,M17/N17) -> 6250 | R17: =IF(O17=0,0,+Q17/O17-1) -> 0 | S17: 9
B18: 1.9 | C18: DEMOLIÇÃO DE FUNDAÇÃO | D18: vb | E18: 1 | F18: 0 | G18: 4100 | H18: =E18*F18 -> 0 | I18: =E18*G18 -> 4100 | L18: =E18*F18 -> 0 | O18: =L18+I18 -> 4100 | Q18: =IF(K18="",I18,J18/K18)+IF(N18="",L18,M18/N18) -> 4100 | R18: =IF(O18=0,0,+Q18/O18-1) -> 0
B19: 2 | C19: FUNDAÇÕES EM SAPATAS, LAJE DE PISO | E19: =SUM(E20:E33) -> 4111.74 | H19: =SUM(H20:H33) -> 185580.7 | I19: =SUM(I20:I33) -> 176404.95 | K19: =SUM(K20:K33)/COUNT(K20:K33) -> #DIV/0! | L19: =SUM(L20:L33) -> 191827.38 | N19: =SUM(N20:N33)/COUNT(N20:N33) -> #DIV/0! | O19: =SUM(O20:O33) -> 368232.33 | Q19: =SUM(Q20:Q33) -> 368232.33 | R19: =IF(O19=0,0,+Q19/O19-1) -> 0 | S19: 10
A20: =$B$19&"."&B20 -> 2.2.1 | B20: 2.1 | C20: ESCAVAÇÃO MANUAL DE VALA EM SOLO DE 1ª CATEGORIA, PROFUNDIDADE ENTRE 1,5 E 4,0 M | D20: m3 | E20: 192.27 | F20: 10.25 | G20: 18.45 | H20: =E20*F20 -> 1970.7675 | I20: =E20*G20+(4000) -> 7547.3815 | L20: =E20*F20 -> 1970.7675 | O20: =L20+I20 -> 9518.149 | Q20: =IF(K20="",I20,J20/K20)+IF(N20="",L20,M20/N20) -> 9518.149 | R20: =IF(O20=0,0,+Q20/O20-1) -> 0 | S20: 11
A21: =$B$19&"."&B21 -> 2.2.2 | B21: 2.2 | C21: APILOAMENTO DE FUNDO DE VALAS | D21: m2 | E21: =300+300 -> 600 | F21: 1.5 | G21: 2.2 | H21: =E21*F21 -> 900 | I21: =E21*G21 -> 1320 | L21: =E21*F21 -> 900 | O21: =L21+I21 -> 2220 | Q21: =IF(K21="",I21,J21/K21)+IF(N21="",L21,M21/N21) -> 2220 | R21: =IF(O21=0,0,+Q21/O21-1) -> 0 | S21: 12
A22: =$B$19&"."&B22 -> 2.2.3 | B22: 2.3 | C22: CONCRETO MAGRO, CONFECÇÃO E LANÇAMENTO (FCK=6MPA) | D22: m3 | E22: =12.65+5 -> 17.65 | F22: 290 | G22: 110 | H22: =E22*F22 -> 5118.5 | I22: =E22*G22 -> 1941.5 | L22: =E22*F22 -> 5118.5 | O22: =L22+I22 -> 7060 | Q22: =IF(K22="",I22,J22/K22)+IF(N22="",L22,M22/N22) -> 7060 | R22: =IF(O22=0,0,+Q22/O22-1) -> 0 | S22: 13
A23: =$B$19&"."&B23 -> 2.2.4 | B23: 2.4 | C23: FABRICAÇÃO, MONTAGEM E DESMONTAGEM DE FÔRMA (1 REAPROVEITAMENTO / 2 USOS) - FUNDAÇÃO | D23: m2 | E23: 248.65 | F23: 55.65 | G23: 80 | H23: =E23*F23 -> 13837.372 | I23: =E23*G23+(2880) -> 22772 | L23: =E23*F23 + (2482.2) -> 16319.572 | O23: =L23+I23 -> 39091.572 | Q23: =IF(K23="",I23,J23/K23)+IF(N23="",L23,M23/N23) -> 39091.572 | R23: =IF(O23=0,0,+Q23/O23-1) -> 0 | S23: 14
A24: =$B$19&"."&B24 -> 2.2.5 | B24: 2.5 | C24: ARMAÇÃO AÇO CA-50 (FUNDAÇÃO) | D24: kg | E24: 1911.4 | F24: 9.5 | G24: 4.2 | H24: =E24*F24 -> 18158.3 | I24: =E24*G24 + (2823.36) -> 10851.24 | L24: =E24*F24 + (3764.48) -> 21922.78 | O24: =L24+I24 -> 32774.02 | Q24: =IF(K24="",I24,J24/K24)+IF(N24="",L24,M24/N24) -> 32774.02 | R24: =IF(O24=0,0,+Q24/O24-1) -> 0 | S24: 15
A25: =$B$19&"."&B25 -> 2.2.6 | B25: 2.6 | C25: CONCRETO FCK = 30MPA, PREPARO MECÂNICO COM BETONEIRA (FUNDAÇÃO) | D25: m3 | E25: =58.96+23.5 -> 82.46 | F25: 550 | G25: 160 | H25: =E25*F25 -> 45353 | I25: =E25*G25 -> 13193.6 | L25: =E25*F25 -> 45353 | O25: =L25+I25 -> 58546.6 | Q25: =IF(K25="",I25,J25/K25)+IF(N25="",L25,M25/N25) -> 58546.6 | R25: =IF(O25=0,0,+Q25/O25-1) -> 0 | S25: 16
A26: =$B$19&"."&B26 -> 2.2.7 | B26: 2.7 | C26: CARGA E BOTA FORA DE TERRA | D26: m3 | E26: 200 | F26: 0 | G26: 25.56 | H26: =E26*F26 -> 0 | I26: =E26*G26 -> 5112 | L26: =E26*F26 -> 0 | O26: =L26+I26 -> 5112 | Q26: =IF(K26="",I26,J26/K26)+IF(N26="",L26,M26/N26) -> 5112 | R26: =IF(O26=0,0,+Q26/O26-1) -> 0 | S26: 17
A27: =$B$19&"."&B27 -> 2.2.8 | B27: 2.8 | C27: CONTENÇÃO EM BLOCO DE CONCRETO | D27: m2 | E27: 464.31 | F27: 85.56 | G27: 165.32 | H27: =E27*F27 -> 39726.364 | I27: =E27*G27 -> 76759.729 | L27: =E27*F27 -> 39726.364 | O27: =L27+I27 -> 116486.09 | Q27: =IF(K27="",I27,J27/K27)+IF(N27="",L27,M27/N27) -> 116486.09 | S27: 18
A28: =$B$19&"."&B28 -> 2.2.9 | B28: 2.9 | C28: IMPERMEABILIZAÇÃO DE BALDRAMES E CONTENÇÕES | D28: vb | E28: 1 | F28: 14650 | G28: 12456 | H28: =E28*F28 -> 14650 | I28: =E28*G28 -> 12456 | L28: =E28*F28 -> 14650 | O28: =L28+I28 -> 27106 | Q28: =IF(K28="",I28,J28/K28)+IF(N28="",L28,M28/N28) -> 27106 | R28: =IF(O28=0,0,+Q28/O28-1) -> 0 | S28: 19
A29: =$B$19&"."&B29 -> 2.2.10 | B29: 2.10 | C29: ESTRUTURA PARA ESCADA INTERNA SUBSOLO | D29: vb | E29: 1 | F29: 7569 | G29: 5650 | H29: =E29*F29 -> 7569 | I29: =E29*G29 -> 5650 | L29: =E29*F29 -> 7569 | O29: =L29+I29 -> 13219 | Q29: =IF(K29="",I29,J29/K29)+IF(N29="",L29,M29/N29) -> 13219 | R29: =IF(O29=0,0,+Q29/O29-1) -> 0 | S29: 20
A30: =$B$19&"."&B30 -> 2.2.11 | B30: 2.11 | C30: CALHA PARA CAPTAÇÃO ÁGUA SUBSOLO | D30: vb | E30: 1 | F30: 1400 | G30: 900 | H30: =E30*F30 -> 1400 | I30: =E30*G30 -> 900 | L30: =E30*F30 -> 1400 | O30: =L30+I30 -> 2300 | Q30: =IF(K30="",I30,J30/K30)+IF(N30="",L30,M30/N30) -> 2300 | S30: 21
A31: =$B$19&"."&B31 -> 2.2.12 | B31: 2.12 | C31: SISTEMA DE BOMBA PARA FUNDAÇÃO | D31: vb | E31: 1 | F31: =9650+13000 -> 22650 | G31: 4560 | H31: =E31*F31 -> 22650 | I31: =E31*G31 -> 4560 | L31: =E31*F31 -> 22650 | O31: =L31+I31 -> 27210 | Q31: =IF(K31="",I31,J31/K31)+IF(N31="",L31,M31/N31) -> 27210 | S31: 22
A32: =$B$19&"."&B32 -> 2.2.13 | B32: 2.13 | C32: ESTRUTURA PARA ESCADA EXTERNA | D32: vb | E32: 1 | F32: 8569 | G32: 4859 | H32: =E32*F32 -> 8569 | I32: =E32*G32 -> 4859 | L32: =E32*F32 -> 8569 | O32: =L32+I32 -> 13428 | Q32: =IF(K32="",I32,J32/K32)+IF(N32="",L32,M32/N32) -> 13428 | R32: =IF(O32=0,0,+Q32/O32-1) -> 0 | S32: 23
A33: =$B$19&"."&B33 -> 2.2.14 | B33: 2.14 | C33: REATERRO MANUAL APILOADO | D33: m2 | E33: =195+195 -> 390 | F33: 14.56 | G33: 21.75 | H33: =E33*F33 -> 5678.4 | I33: =E33*G33 -> 8482.5 | L33: =E33*F33 -> 5678.4 | O33: =L33+I33 -> 14160.9 | Q33: =IF(K33="",I33,J33/K33)+IF(N33="",L33,M33/N33) -> 14160.9 | R33: =IF(O33=0,0,+Q33/O33-1) -> 0 | S33: 24
B34: 3 | C34: SUPRA ESTRUTURA (ESTIMATIVA SEM PROJETO) | D34: vb | E34: 1 | F34: 8569 | G34: 4859 | H34: =E34*F34 -> 8569 | I34: =SUM(I35:I40) -> 103630.63 | L34: =SUM(L35:L40) -> 199902.18 | O34: =SUM(O35:O40) -> 303532.81 | Q34: =SUM(Q35:Q40) -> 303532.81 | R34: =IF(O34=0,0,+Q34/O34-1) -> 0 | S34: 25
A35: =$B$34&"."&B35 -> 3.3.1 | B35: 3.1 | C35: MONTAGEM E DESMONTAGEM DE FÔRMA DE PILARES EM PLASTIFICADO 12MM (1 REAPROVEITAMENTO / 2 USOS) - SUPRA ESTRUTURA | D35: m2 | E35: 425.36 | F35: 57.85 | G35: 55.65 | H35: =E35*F35 -> 24607.076 | I35: =E35*G35 -> 23671.284 | L35: =E35*F35 -> 24607.076 | O35: =L35+I35 -> 48278.36 | Q35: =IF(K35="",I35,J35/K35)+IF(N35="",L35,M35/N35) -> 48278.36 | R35: =IF(O35=0,0,+Q35/O35-1) -> 0 | S35: 26
A36: =$B$34&"."&B36 -> 3.3.2 | B36: 3.2 | C36: ARMAÇÃO AÇO CA-50 (SUPRA ESTRUTURA) | D36: kg | E36: 6988.8 | F36: 9.5 | G36: 4.2 | H36: =G36+F36 -> 13.7 | I36: =E36*G36 -> 29352.96 | L36: =E36*F36 -> 66393.6 | O36: =L36+I36 -> 95746.56 | Q36: =IF(K36="",I36,J36/K36)+IF(N36="",L36,M36/N36) -> 95746.56 | R36: =IF(O36=0,0,+Q36/O36-1) -> 0 | S36: 27
A37: =$B$34&"."&B37 -> 3.3.3 | B37: 3.3 | C37: CONCRETO FCK = 30MPA, PREPARO MECÂNICO COM BETONEIRA (SUPRA ESTRUTURA) | D37: m3 | E37: 75.45 | F37: 550 | G37: 155 | H37: =G37+F37 -> 705 | I37: =E37*G37 -> 11694.75 | L37: =E37*F37 -> 41497.5 | O37: =L37+I37 -> 53192.25 | Q37: =IF(K37="",I37,J37/K37)+IF(N37="",L37,M37/N37) -> 53192.25 | R37: =IF(O37=0,0,+Q37/O37-1) -> 0 | S37: 28
A38: =$B$34&"."&B38 -> 3.3.4 | B38: 3.4 | C38: LAJE PRE-MOLD COM BLOCO DE EPS H=21CM, COM CAPEAMENTO H=5 CM | D38: m2 | E38: 436 | F38: 112.56 | G38: 35.65 | H38: =G38+F38 -> 148.21 | I38: =E38*G38 -> 15543.4 | L38: =E38*F38 -> 49076.16 | O38: =L38+I38 -> 64619.56 | Q38: =IF(K38="",I38,J38/K38)+IF(N38="",L38,M38/N38) -> 64619.56 | R38: =IF(O38=0,0,+Q38/O38-1) -> 0 | S38: 29
A39: =$B$34&"."&B39 -> 3.3.5 | B39: 3.5 | C39: ESCORAMENTO DE LAJE PRE-MOLDADA E VIGAS | D39: m2 | E39: 654 | F39: 15.96 | G39: 18.56 | H39: =G39+F39 -> 34.52 | I39: =E39*G39 -> 12138.24 | L39: =E39*F39 -> 10437.84 | O39: =L39+I39 -> 22576.08 | Q39: =IF(K39="",I39,J39/K39)+IF(N39="",L39,M39/N39) -> 22576.08 | R39: =IF(O39=0,0,+Q39/O39-1) -> 0 | S39: 30
A40: =$B$34&"."&B40 -> 3.3.6 | B40: 3.6 | C40: ESTRUTURA PARA ESCADA EM CONCRETO | D40: und | E40: 1 | F40: 7890 | G40: 11230 | H40: =G40+F40 -> 19120 | I40: =E40*G40 -> 11230 | L40: =E40*F40 -> 7890 | O40: =L40+I40 -> 19120 | Q40: =IF(K40="",I40,J40/K40)+IF(N40="",L40,M40/N40) -> 19120 | R40: =IF(O40=0,0,+Q40/O40-1) -> 0 | S40: 31
B41: 4 | C41: ALVENARIAS E FECHAMENTOS | E41: =SUM(E42:E51) -> 3663.11 | H41: =SUM(H42:H51) -> 42488.34 | I41: =SUM(I42:I51) -> 107742.46 | L41: =SUM(L42:L51) -> 65432.829 | O41: =SUM(O42:O51) -> 173175.28 | Q41: =SUM(Q42:Q51) -> 173175.28 | R41: =IF(O41=0,0,+Q41/O41-1) -> 0 | S41: 32
A42: =$B$41&"."&B42 -> 4.4.1 | B42: 4.1 | C42: ALVENARIA DE VEDAÇÃO DE BLOCOS CERÂMICOS FURADOS NA HORIZONTAL DE 9X19X24 CM (ESPESSURA 15 CM) COM ARGAMASSA DE CIMENTO E AREIA | D42: m2 | E42: 1538.28 | F42: 32.56 | G42: 32.56 | H42: =G42+F42 -> 65.12 | I42: =E42*G42 -> 50086.397 | L42: =E42*F42 -> 50086.397 | O42: =L42+I42 -> 100172.79 | Q42: =IF(K42="",I42,J42/K42)+IF(N42="",L42,M42/N42) -> 100172.79 | R42: =IF(O42=0,0,+Q42/O42-1) -> 0 | S42: 33
A43: =$B$41&"."&B43 -> 4.4.2 | B43: 4.2 | C43: PONTO DE MASSA (ALVENARIA) | D43: m2 | E43: 1538.28 | F43: 4.02 | G43: 2.5 | H43: =G43+F43 -> 6.52 | I43: =E43*G43 -> 3845.7 | L43: =E43*F43 -> 6183.8856 | O43: =L43+I43 -> 10029.586 | Q43: =IF(K43="",I43,J43/K43)+IF(N43="",L43,M43/N43) -> 10029.586 | R43: =IF(O43=0,0,+Q43/O43-1) -> 0 | S43: 34
A44: =$B$41&"."&B44 -> 4.4.3 | B44: 4.3 | C44: ARESTAMENTOS DIVERSOS | D44: vb | E44: 1 | F44: 1895 | G44: 10560 | H44: =G44+F44 -> 12455 | I44: =E44*G44 -> 10560 | L44: =E44*F44 -> 1895 | O44: =L44+I44 -> 12455 | Q44: =IF(K44="",I44,J44/K44)+IF(N44="",L44,M44/N44) -> 12455 | R44: =IF(O44=0,0,+Q44/O44-1) -> 0 | S44: 35
A45: =$B$41&"."&B45 -> 4.4.4 | B45: 4.4 | C45: ESQUADRIAS E PORTAS EM MADEIRA | D45: und | E45: 33 | G45: 250 | H45: =G45+F45 -> 250 | I45: =E45*G45 -> 8250 | L45: =E45*F45 -> 0 | O45: =L45+I45 -> 8250 | Q45: =IF(K45="",I45,J45/K45)+IF(N45="",L45,M45/N45) -> 8250 | R45: =IF(O45=0,0,+Q45/O45-1) -> 0 | S45: 36
A46: =$B$41&"."&B46 -> 4.4.5 | B46: 4.5 | C46: PORTA PRINCIPAL EM MADEIRA | D46: vb | E46: 1 | H46: =G46+F46 -> 0 | I46: =E46*G46 -> 0 | L46: =E46*F46 -> 0 | O46: =L46+I46 -> 0 | Q46: =IF(K46="",I46,J46/K46)+IF(N46="",L46,M46/N46) -> 0 | R46: =IF(O46=0,0,+Q46/O46-1) -> 0 | S46: 37
A47: =$B$41&"."&B47 -> 4.4.6 | B47: 4.6 | C47: APERTO COMUM EM PAREDES | D47: ml | E47: 512.76 | F47: 8.69 | G47: 6.57 | H47: =G47+F47 -> 15.26 | I47: =E47*G47 -> 3368.8332 | L47: =E47*F47 -> 4455.8844 | O47: =L47+I47 -> 7824.7176 | Q47: =IF(K47="",I47,J47/K47)+IF(N47="",L47,M47/N47) -> 7824.7176 | R47: =IF(O47=0,0,+Q47/O47-1) -> 0 | S47: 38
A48: =$B$41&"."&B48 -> 4.4.7 | B48: 4.7 | C48: ESQUADRIAS E VIDROS EM ALUMINIO | D48: vb | E48: 1 | H48: =G48+F48 -> 0 | I48: =E48*G48 -> 0 | L48: =E48*F48 -> 0 | O48: =L48+I48 -> 0 | Q48: =IF(K48="",I48,J48/K48)+IF(N48="",L48,M48/N48) -> 0 | R48: =IF(O48=0,0,+Q48/O48-1) -> 0 | S48: 39
A49: =$B$41&"."&B49 -> 4.4.8 | B49: 4.8 | C49: GUARDA CORPO EM MADEIRA E VIDRO | D49: vb | E49: 1 | H49: =G49+F49 -> 0 | I49: =E49*G49 -> 0 | L49: =E49*F49 -> 0 | O49: =L49+I49 -> 0 | Q49: =IF(K49="",I49,J49/K49)+IF(N49="",L49,M49/N49) -> 0 | R49: =IF(O49=0,0,+Q49/O49-1) -> 0 | S49: 40
A50: =$B$41&"."&B50 -> 4.4.9 | B50: 4.9 | C50: VERGA EM CONCRETO | D50: ml | E50: 35.79 | F50: 78.56 | G50: 57.88 | H50: =G50+F50 -> 136.44 | I50: =E50*G50 -> 2071.5252 | L50: =E50*F50 -> 2811.6624 | O50: =L50+I50 -> 4883.1876 | Q50: =IF(K50="",I50,J50/K50)+IF(N50="",L50,M50/N50) -> 4883.1876 | R50: =IF(O50=0,0,+Q50/O50-1) -> 0 | S50: 41
A51: =$B$41&"."&B51 -> 4.4.10 | B51: 4.10 | C51: FACHADA EM MADEIRA (RIPADOS, BRISES, ETC) | D51: vb | E51: 1 | G51: 29560 | H51: =G51+F51 -> 29560 | I51: =E51*G51 -> 29560 | L51: =E51*F51 -> 0 | O51: =L51+I51 -> 29560 | Q51: =IF(K51="",I51,J51/K51)+IF(N51="",L51,M51/N51) -> 29560 | R51: =IF(O51=0,0,+Q51/O51-1) -> 0 | S51: 42
B52: 5.1 | C52: REVESTIMENTOS PAREDE | E52: =SUM(E53:E58) -> 10130.57 | H52: =SUM(H53:H58) -> 308.22 | I52: =SUM(I53:I58) -> 183374.26 | L52: =SUM(L53:L58) -> 76914 | O52: =SUM(O53:O58) -> 260288.26 | Q52: =SUM(Q53:Q58) -> 260288.26 | R52: =IF(O52=0,0,+Q52/O52-1) -> 0 | S52: 43
A53: =$B$52&"."&B53 -> 5.1.5.1.1 | B53: 5.1.1 | C53: CHAPISCO | D53: m2 | E53: 3076.56 | F53: 3.54 | G53: 6.6 | H53: =G53+F53 -> 10.14 | I53: =E53*G53 -> 20305.296 | L53: =E53*F53 -> 10891.022 | O53: =L53+I53 -> 31196.318 | Q53: =IF(K53="",I53,J53/K53)+IF(N53="",L53,M53/N53) -> 31196.318 | R53: =IF(O53=0,0,+Q53/O53-1) -> 0 | S53: 44
A54: =$B$52&"."&B54 -> 5.1.5.1.2 | B54: 5.1.2 | C54: MASSA ÚNICA EM PAREDES | D54: m2 | E54: 3076.56 | F54: 17.44 | G54: 34.56 | H54: =G54+F54 -> 52 | I54: =E54*G54 -> 106325.91 | L54: =E54*F54 -> 53655.206 | O54: =L54+I54 -> 159981.12 | Q54: =IF(K54="",I54,J54/K54)+IF(N54="",L54,M54/N54) -> 159981.12 | R54: =IF(O54=0,0,+Q54/O54-1) -> 0 | S54: 45
A55: =$B$52&"."&B55 -> 5.1.5.1.3 | B55: 5.1.3 | C55: PONTO DE MASSA (REVESTIMENTO DE PAREDE) | D55: m2 | E55: 3076.56 | F55: 4.02 | G55: 2.5 | H55: =G55+F55 -> 6.52 | I55: =E55*G55 -> 7691.4 | L55: =E55*F55 -> 12367.771 | O55: =L55+I55 -> 20059.171 | Q55: =IF(K55="",I55,J55/K55)+IF(N55="",L55,M55/N55) -> 20059.171 | R55: =IF(O55=0,0,+Q55/O55-1) -> 0 | S55: 46
A56: =$B$52&"."&B56 -> 5.1.5.1.4 | B56: 5.1.4 | C56: INSTALAÇÃO DE REVESTIMENTO EM PORCELANATO | D56: m2 | E56: 401.82 | G56: 60 | H56: =G56+F56 -> 60 | I56: =E56*G56 -> 24109.2 | L56: =E56*F56 -> 0 | O56: =L56+I56 -> 24109.2 | Q56: =IF(K56="",I56,J56/K56)+IF(N56="",L56,M56/N56) -> 24109.2 | R56: =IF(O56=0,0,+Q56/O56-1) -> 0 | S56: 47
A57: =$B$52&"."&B57 -> 5.1.5.1.5 | B57: 5.1.5 | C57: REJUNTAMENTO EM PORCELANATO | D57: m2 | E57: 401.82 | G57: 24.56 | H57: =G57+F57 -> 24.56 | I57: =E57*G57 -> 9868.6992 | L57: =E57*F57 -> 0 | O57: =L57+I57 -> 9868.6992 | Q57: =IF(K57="",I57,J57/K57)+IF(N57="",L57,M57/N57) -> 9868.6992 | R57: =IF(O57=0,0,+Q57/O57-1) -> 0 | S57: 48
A58: =$B$52&"."&B58 -> 5.1.5.1.6 | B58: 5.1.6 | C58: REVESTIMENTO EM PEDRA NATURAL | D58: m2 | E58: 97.25 | G58: 155 | H58: =G58+F58 -> 155 | I58: =E58*G58 -> 15073.75 | L58: =E58*F58 -> 0 | O58: =L58+I58 -> 15073.75 | Q58: =IF(K58="",I58,J58/K58)+IF(N58="",L58,M58/N58) -> 15073.75 | R58: =IF(O58=0,0,+Q58/O58-1) -> 0 | S58: 49
B59: 5.2 | C59: REVESTIMENTOS TETO | E59: =SUM(E60:E64) -> 1205.0125 | H59: =SUM(H60:H64) -> 3270.79 | I59: =SUM(I60:I64) -> 66796.81 | L59: =SUM(L60:L64) -> 16735.741 | O59: =SUM(O60:O64) -> 83532.551 | Q59: =SUM(Q60:Q64) -> 83532.551 | R59: =IF(O59=0,0,+Q59/O59-1) -> 0 | S59: 50
A60: =$B$59&"."&B60 -> 5.2.5.2.1 | B60: 5.2.1 | C60: FORRO EM DRYWALL, PARA AMBIENTES RESIDENCIAIS, INCLUSIVE ESTRUTURA DE FIXAÇÃO | D60: m2 | E60: 139.15 | F60: 62.56 | G60: 35 | H60: =G60+F60 -> 97.56 | I60: =E60*G60 -> 4870.25 | L60: =E60*F60 -> 8705.224 | O60: =L60+I60 -> 13575.474 | Q60: =IF(K60="",I60,J60/K60)+IF(N60="",L60,M60/N60) -> 13575.474 | R60: =IF(O60=0,0,+Q60/O60-1) -> 0 | S60: 51
A61: =$B$59&"."&B61 -> 5.2.5.2.2 | B61: 5.2.2 | C61: FORRO PARA BEIRAL E TELHADO E INTERNO EM RIPADO CUMARU | D61: m2 | E61: =57495.11/G61 -> 547.57248 | F61: 0 | G61: 105 | H61: =G61+F61 -> 105 | I61: =E61*G61 -> 57495.11 | L61: =E61*F61 -> 0 | O61: =L61+I61 -> 57495.11 | Q61: =IF(K61="",I61,J61/K61)+IF(N61="",L61,M61/N61) -> 57495.11 | R61: =IF(O61=0,0,+Q61/O61-1) -> 0 | S61: 52
A62: =$B$59&"."&B62 -> 5.2.5.2.3 | B62: 5.2.3 | C62: EXECUÇÃO DE ALÇAPÃO DE GESSO ACARTONADO | D62: und | E62: 1 | F62: 350 | G62: 200 | H62: =G62+F62 -> 550 | I62: =E62*G62 -> 200 | L62: =E62*F62 -> 350 | O62: =L62+I62 -> 550 | Q62: =IF(K62="",I62,J62/K62)+IF(N62="",L62,M62/N62) -> 550 | R62: =IF(O62=0,0,+Q62/O62-1) -> 0 | S62: 53
A63: =$B$59&"."&B63 -> 5.2.5.2.4 | B63: 5.2.4 | C63: TABICA METÁLICA 3X3 CM | D63: ml | E63: 516.29 | F63: 13.23 | G63: 5 | H63: =G63+F63 -> 18.23 | I63: =E63*G63 -> 2581.45 | L63: =E63*F63 -> 6830.5167 | O63: =L63+I63 -> 9411.9667 | Q63: =IF(K63="",I63,J63/K63)+IF(N63="",L63,M63/N63) -> 9411.9667 | R63: =IF(O63=0,0,+Q63/O63-1) -> 0 | S63: 54
A64: =$B$59&"."&B64 -> 5.2.5.2.5 | B64: 5.2.5 | C64: RECOMPOSIÇÃO DE FORRO EM GESSO | D64: vb | E64: 1 | F64: 850 | G64: 1650 | H64: =G64+F64 -> 2500 | I64: =E64*G64 -> 1650 | L64: =E64*F64 -> 850 | O64: =L64+I64 -> 2500 | Q64: =IF(K64="",I64,J64/K64)+IF(N64="",L64,M64/N64) -> 2500 | R64: =IF(O64=0,0,+Q64/O64-1) -> 0 | S64: 55
B65: 6 | C65: PAVIMENTAÇÃO | E65: =SUM(E66:E72) -> 3086.39 | H65: =SUM(H66:H73) -> 417.88 | I65: =SUM(I66:I73) -> 98538.747 | L65: =SUM(L66:L73) -> 25794.013 | O65: =SUM(O66:O73) -> 124332.76 | Q65: =SUM(Q66:Q73) -> 124332.76 | R65: =IF(O65=0,0,+Q65/O65-1) -> 0 | S65: 56
A66: =$B$65&"."&B66 -> 6.6.1 | B66: 6.1 | C66: CONTRAPISO EM ARGAMASSA CIMENTO E AREIA, ESPESSURA 3 CM | D66: m2 | E66: 792.93 | F66: 28.51 | G66: 32.65 | H66: =G66+F66 -> 61.16 | I66: =E66*G66 -> 25889.164 | L66: =E66*F66 -> 22606.434 | O66: =L66+I66 -> 48495.599 | Q66: =IF(K66="",I66,J66/K66)+IF(N66="",L66,M66/N66) -> 48495.599 | R66: =IF(O66=0,0,+Q66/O66-1) -> 0 | S66: 57
A67: =$B$65&"."&B67 -> 6.6.2 | B67: 6.2 | C67: PONTO DE MASSA (PAVIMENTAÇÃO) | D67: m2 | E67: 792.93 | F67: 4.02 | G67: 3.5 | H67: =G67+F67 -> 7.52 | I67: =E67*G67 -> 2775.255 | L67: =E67*F67 -> 3187.5786 | O67: =L67+I67 -> 5962.8336 | Q67: =IF(K67="",I67,J67/K67)+IF(N67="",L67,M67/N67) -> 5962.8336 | R67: =IF(O67=0,0,+Q67/O67-1) -> 0 | S67: 58
A68: =$B$65&"."&B68 -> 6.6.3 | B68: 6.3 | C68: INSTALAÇÃO DE PISO PERMEÁVEL | D68: m2 | E68: 67.32 | G68: 60 | H68: =G68+F68 -> 60 | I68: =E68*G68 -> 4039.2 | L68: =E68*F68 -> 0 | O68: =L68+I68 -> 4039.2 | Q68: =IF(K68="",I68,J68/K68)+IF(N68="",L68,M68/N68) -> 4039.2 | R68: =IF(O68=0,0,+Q68/O68-1) -> 0 | S68: 59
A69: =$B$65&"."&B69 -> 6.6.4 | B69: 6.4 | C69: INSTALAÇÃO DE PISO EM PORCELANATO | D69: m2 | E69: 520.27 | G69: 60 | H69: =G69+F69 -> 60 | I69: =E69*G69 -> 31216.2 | L69: =E69*F69 -> 0 | O69: =L69+I69 -> 31216.2 | Q69: =IF(K69="",I69,J69/K69)+IF(N69="",L69,M69/N69) -> 31216.2 | R69: =IF(O69=0,0,+Q69/O69-1) -> 0 | S69: 60
A70: =$B$65&"."&B70 -> 6.6.5 | B70: 6.5 | C70: INSTALAÇÃO DE RODAPÉ METALICO | D70: ml | E70: 188.37 | G70: 25 | H70: =G70+F70 -> 25 | I70: =E70*G70 -> 4709.25 | L70: =E70*F70 -> 0 | O70: =L70+I70 -> 4709.25 | Q70: =IF(K70="",I70,J70/K70)+IF(N70="",L70,M70/N70) -> 4709.25 | R70: =IF(O70=0,0,+Q70/O70-1) -> 0 | S70: 61
A71: =$B$65&"."&B71 -> 6.6.6 | B71: 6.6 | C71: INSTALAÇÃO DE DECK EM MADEIRA | D71: m2 | E71: 136.98 | G71: 125 | H71: =G71+F71 -> 125 | I71: =E71*G71 -> 17122.5 | L71: =E71*F71 -> 0 | O71: =L71+I71 -> 17122.5 | Q71: =IF(K71="",I71,J71/K71)+IF(N71="",L71,M71/N71) -> 17122.5 | R71: =IF(O71=0,0,+Q71/O71-1) -> 0 | S71: 62
A72: =$B$65&"."&B72 -> 6.6.7 | B72: 6.7 | C72: REJUNTAMENTO DE PISOS E RODAPÉS EM PORCELANATO (MAT. + MO) | D72: m2 | E72: 587.59 | G72: 14.2 | H72: =G72+F72 -> 14.2 | I72: =E72*G72 -> 8343.778 | L72: =E72*F72 -> 0 | O72: =L72+I72 -> 8343.778 | Q72: =IF(K72="",I72,J72/K72)+IF(N72="",L72,M72/N72) -> 8343.778 | R72: =IF(O72=0,0,+Q72/O72-1) -> 0 | S72: 63
A73: =$B$65&"."&B73 -> 6.6.8 | B73: 6.8 | C73: PISO INTERTRAVADO | D73: m2 | E73: 68.36 | G73: 65 | H73: =G73+F73 -> 65 | I73: =E73*G73 -> 4443.4 | L73: =E73*F73 -> 0 | O73: =L73+I73 -> 4443.4 | Q73: =IF(K73="",I73,J73/K73)+IF(N73="",L73,M73/N73) -> 4443.4 | R73: =IF(O73=0,0,+Q73/O73-1) -> 0 | S73: 64
B74: 7.1 | C74: FILETE DE BOX E SOLEIRA | E74: =SUM(E75:E76) -> 42.26 | H74: =SUM(H75:H76) -> 101 | I74: =SUM(I75:I76) -> 1413.75 | L74: =SUM(L75:L76) -> 712.32 | O74: =SUM(O75:O76) -> 2126.07 | Q74: =SUM(Q75:Q76) -> 2126.07 | R74: =IF(O74=0,0,+Q74/O74-1) -> 0 | S74: 65
A75: =$B$74&"."&B75 -> 7.1.7.1.1 | B75: 7.1.1 | C75: COLOCAÇÃO DE FILETE PARA BOX EM MÁRMORE | D75: ml | E75: 13.07 | F75: 21 | G75: 30 | H75: =G75+F75 -> 51 | I75: =E75*G75 -> 392.1 | L75: =E75*F75 -> 274.47 | O75: =L75+I75 -> 666.57 | Q75: =IF(K75="",I75,J75/K75)+IF(N75="",L75,M75/N75) -> 666.57 | R75: =IF(O75=0,0,+Q75/O75-1) -> 0 | S75: 66
A76: =$B$74&"."&B76 -> 7.1.7.1.2 | B76: 7.1.2 | C76: COLOCAÇÃO DE SOLEIRA EM MÁRMORE, LARGURA 15 CM | D76: ml | E76: 29.19 | F76: 15 | G76: 35 | H76: =G76+F76 -> 50 | I76: =E76*G76 -> 1021.65 | L76: =E76*F76 -> 437.85 | O76: =L76+I76 -> 1459.5 | Q76: =IF(K76="",I76,J76/K76)+IF(N76="",L76,M76/N76) -> 1459.5 | R76: =IF(O76=0,0,+Q76/O76-1) -> 0 | S76: 67
B77: 7.2 | C77: BANCADA | E77: =SUM(E78:E80) -> 86.39 | H77: =SUM(H78:H80) -> 325 | I77: =SUM(I78:I80) -> 13879.35 | L77: =SUM(L78:L80) -> 1959.75 | O77: =SUM(O78:O80) -> 15839.1 | Q77: =SUM(Q78:Q80) -> 15839.1 | R77: =IF(O77=0,0,+Q77/O77-1) -> 0 | S77: 68
A78: =$B$77&"."&B78 -> 7.2.7.2.1 | B78: 7.2.1 | C78: ASSENTAMENTO DE BANCADA | D78: ml | E78: 78.39 | F78: 25 | G78: 165 | H78: =G78+F78 -> 190 | I78: =E78*G78 -> 12934.35 | L78: =E78*F78 -> 1959.75 | O78: =L78+I78 -> 14894.1 | Q78: =IF(K78="",I78,J78/K78)+IF(N78="",L78,M78/N78) -> 14894.1 | R78: =IF(O78=0,0,+Q78/O78-1) -> 0 | S78: 69
A79: =$B$77&"."&B79 -> 7.2.7.2.2 | B79: 7.2.2 | C79: FORNECIMENTO DE MARMORES | D79: vb | E79: 1 | F79: 0 | H79: =G79+F79 -> 0 | I79: =E79*G79 -> 0 | L79: =E79*F79 -> 0 | O79: =L79+I79 -> 0 | Q79: =IF(K79="",I79,J79/K79)+IF(N79="",L79,M79/N79) -> 0 | R79: =IF(O79=0,0,+Q79/O79-1) -> 0 | S79: 70
A80: =$B$77&"."&B80 -> 7.2.7.2.3 | B80: 7.2.3 | C80: COLOCAÇÃO DE NICHO EM MARMÓRE, COM CORTE E ARESTAMENTO DE VÃO | D80: und | E80: 7 | G80: 135 | H80: =G80+F80 -> 135 | I80: =E80*G80 -> 945 | L80: =E80*F80 -> 0 | O80: =L80+I80 -> 945 | Q80: =IF(K80="",I80,J80/K80)+IF(N80="",L80,M80/N80) -> 945 | R80: =IF(O80=0,0,+Q80/O80-1) -> 0 | S80: 71
B81: 8 | C81: LOUÇAS E METAIS | E81: =SUM(E82:E84) -> 3 | H81: =SUM(H82:H84) -> 3606 | I81: =SUM(I82:I84) -> 4339 | L81: =SUM(L82:L84) -> 956 | O81: =SUM(O82:O84) -> 5295 | Q81: =SUM(Q82:Q84) -> 5295 | R81: =IF(O81=0,0,+Q81/O81-1) -> 0 | S81: 72
A82: =$B$81&"."&B82 -> 8.8.1 | B82: 8.1 | C82: INSTALAÇÕES LOUÇAS E METAIS | D82: vb | E82: 1 | F82: 956 | G82: 2650 | H82: =F82+G82 -> 3606 | I82: =E82*G82 -> 2650 | L82: =E82*F82 -> 956 | O82: =L82+I82 -> 3606 | Q82: =IF(K82="",I82,J82/K82)+IF(N82="",L82,M82/N82) -> 3606 | R82: =IF(O82=0,0,+Q82/O82-1) -> 0 | S82: 73
A83: =$B$81&"."&B83 -> 8.8.2 | B83: 8.2 | C83: LOUÇAS E METAIS (MATERIAL) | D83: vb | E83: 1 | F83: 0 | H83: =F83+G83 -> 0 | I83: =E83*G83 -> 0 | L83: =E83*F83 -> 0 | O83: =L83+I83 -> 0 | Q83: =IF(K83="",I83,J83/K83)+IF(N83="",L83,M83/N83) -> 0 | R83: =IF(O83=0,0,+Q83/O83-1) -> 0 | S83: 74
A84: =$B$81&"."&B84 -> 8.8.3 | B84: 8.3 | C84: INSTALAÇÃO DE ACESSORIOS | D84: vb | E84: 1 | G84: 1689 | H84: 0 | I84: =E84*G84 -> 1689 | L84: =E84*F84 -> 0 | O84: =L84+I84 -> 1689 | Q84: =IF(K84="",I84,J84/K84)+IF(N84="",L84,M84/N84) -> 1689 | R84: =IF(O84=0,0,+Q84/O84-1) -> 0 | S84: 75
B85: 9 | C85: PINTURA | E85: =SUM(E86:E89) -> 1308.1655 | H85: =SUM(H86:H89) -> 287.54 | I85: =SUM(I86:I89) -> 42479.171 | L85: =SUM(L86:L89) -> 48922.23 | O85: =SUM(O86:O89) -> 91401.4 | Q85: =SUM(Q86:Q89) -> 91401.4 | R85: =IF(O85=0,0,+Q85/O85-1) -> 0 | S85: 76
A86: =$B$85&"."&B86 -> 9.9.1 | B86: 9.1 | C86: APLICAÇÃO MANUAL DE TEXTURA EM PAREDES EXTERNAS SOBRE REBOCO, DUAS DEMÃOS | D86: m2 | E86: 142.26 | F86: 49 | G86: 48.56 | H86: =G86+F86 -> 97.56 | I86: =E86*G86 -> 6908.1456 | L86: =E86*F86 -> 6970.74 | O86: =L86+I86 -> 13878.886 | Q86: =IF(K86="",I86,J86/K86)+IF(N86="",L86,M86/N86) -> 13878.886 | R86: =IF(O86=0,0,+Q86/O86-1) -> 0 | S86: 77
A87: =$B$85&"."&B87 -> 9.9.2 | B87: 9.2 | C87: APLICAÇÃO MANUAL DE PINTURA COM TINTA LÁTEX ACRÍLICA COM EMASSAMENTO PVA EM TETO, DUAS DEMÃOS | D87: m2 | E87: 139.15 | F87: 35 | G87: 21.45 | H87: =G87+F87 -> 56.45 | I87: =E87*G87 -> 2984.7675 | L87: =E87*F87 -> 4870.25 | O87: =L87+I87 -> 7855.0175 | Q87: =IF(K87="",I87,J87/K87)+IF(N87="",L87,M87/N87) -> 7855.0175 | R87: =IF(O87=0,0,+Q87/O87-1) -> 0 | S87: 78
A88: =$B$85&"."&B88 -> 9.9.3 | B88: 9.3 | C88: APLICAÇÃO MANUAL DE PINTURA COM TINTA LÁTEX E MASSA ACRÍLICA EM PAREDES INTERNAS, DUAS DEMÃOS | D88: m2 | E88: 381.599 | F88: 38 | G88: 24.53 | H88: =G88+F88 -> 62.53 | I88: =E88*G88 -> 9360.6235 | L88: =E88*F88 -> 14500.762 | O88: =L88+I88 -> 23861.385 | Q88: =IF(K88="",I88,J88/K88)+IF(N88="",L88,M88/N88) -> 23861.385 | R88: =IF(O88=0,0,+Q88/O88-1) -> 0 | S88: 79
A89: =$B$85&"."&B89 -> 9.9.4 | B89: 9.4 | C89: APLICAÇÃO DE VERNIZ TIPO POLIKOL EM FORRO DE MADEIRA, EUCALIPTOS E ESQUADRIAS E PORTAS | D89: m2 | E89: 645.1565 | F89: 35 | G89: 36 | H89: =G89+F89 -> 71 | I89: =E89*G89 -> 23225.634 | L89: =E89*F89 -> 22580.478 | O89: =L89+I89 -> 45806.111 | Q89: =IF(K89="",I89,J89/K89)+IF(N89="",L89,M89/N89) -> 45806.111 | R89: =IF(O89=0,0,+Q89/O89-1) -> 0 | S89: 80
B90: 10 | C90: COBERTURA | E90: =SUM(E91:E93) -> 835.548 | H90: =SUM(H91:H93) -> 728.56 | I90: =SUM(I91:I93) -> 74168.864 | L90: =SUM(L91:L93) -> 109457.06 | O90: =SUM(O91:O93) -> 183625.93 | Q90: =SUM(Q91:Q93) -> 183625.93 | R90: =IF(O90=0,0,+Q90/O90-1) -> 0 | S90: 81
A91: =$B$90&"."&B91 -> 10.10.1 | B91: 10.1 | C91: MADEIRAMENTO COMPLETO EM MAÇARANDUBA APARELHADA PARA TELHADO | D91: m2 | E91: 330.68 | F91: 175 | G91: 110 | H91: =G91+F91 -> 285 | I91: =E91*G91 -> 36374.8 | L91: =E91*F91 -> 57869 | O91: =L91+I91 -> 94243.8 | Q91: =IF(K91="",I91,J91/K91)+IF(N91="",L91,M91/N91) -> 94243.8 | R91: =IF(O91=0,0,+Q91/O91-1) -> 0 | S91: 82
A92: =$B$90&"."&B92 -> 10.10.2 | B92: 10.2 | C92: PERGOLADO EM MADEIRA CUMARU (ESTIMATIVA SEM DETALHAMENTO) | D92: m2 | E92: 58.45 | F92: 0 | G92: 280 | H92: =G92+F92 -> 280 | I92: =E92*G92 -> 16366 | L92: =E92*F92 -> 0 | O92: =L92+I92 -> 16366 | Q92: =IF(K92="",I92,J92/K92)+IF(N92="",L92,M92/N92) -> 16366 | R92: =IF(O92=0,0,+Q92/O92-1) -> 0 | S92: 83
A93: =$B$90&"."&B93 -> 10.10.3 | B93: 10.3 | C93: TELHAMENTO EM TELHA DE CONCRETO | D93: m2 | E93: 446.418 | F93: 115.56 | G93: 48 | H93: =G93+F93 -> 163.56 | I93: =E93*G93 -> 21428.064 | L93: =E93*F93 -> 51588.064 | O93: =L93+I93 -> 73016.128 | Q93: =IF(K93="",I93,J93/K93)+IF(N93="",L93,M93/N93) -> 73016.128 | R93: =IF(O93=0,0,+Q93/O93-1) -> 0 | S93: 84
B94: 11 | C94: LIMPEZA E DIVERSOS | E94: =SUM(E95:E106) -> 1036 | H94: =SUM(H95:H106) -> 66815.51 | I94: =SUM(I95:I106) -> 16024 | L94: =SUM(L95:L106) -> 93910.5 | O94: =SUM(O95:O106) -> 109934.5 | Q94: =SUM(Q95:Q106) -> 109934.5 | R94: =IF(O94=0,0,+Q94/O94-1) -> 0 | S94: 85
A95: =$B$94&"."&B95 -> 11.11.1 | B95: 11.1 | C95: LIMPEZA DE PERMANENTE DE OBRA | D95: mês | E95: 14 | F95: 154.75 | G95: 456 | H95: =G95+F95 -> 610.75 | I95: =E95*G95+(1000) -> 7384 | L95: =E95*F95 -> 2166.5 | O95: =L95+I95 -> 9550.5 | Q95: =IF(K95="",I95,J95/K95)+IF(N95="",L95,M95/N95) -> 9550.5 | R95: =IF(O95=0,0,+Q95/O95-1) -> 0 | S95: 86
A96: =$B$94&"."&B96 -> 11.11.2 | B96: 11.2 | C96: LIMPEZA FINA DE OBRA | D96: vb | E96: 1 | F96: 1890 | G96: 4890 | H96: =G96+F96 -> 6780 | I96: =E96*G96 -> 4890 | L96: =E96*F96 -> 1890 | O96: =L96+I96 -> 6780 | Q96: =IF(K96="",I96,J96/K96)+IF(N96="",L96,M96/N96) -> 6780 | R96: =IF(O96=0,0,+Q96/O96-1) -> 0 | S96: 87
A97: =$B$94&"."&B97 -> 11.11.3 | B97: 11.3 | C97: RETIRADA DE ENTULHO | D97: vb | E97: 1 | F97: =12960 + 1000 -> 13960 | H97: =G97+F97 -> 13960 | I97: =E97*G97 -> 0 | L97: =E97*F97 -> 13960 | O97: =L97+I97 -> 13960 | Q97: =IF(K97="",I97,J97/K97)+IF(N97="",L97,M97/N97) -> 13960 | R97: =IF(O97=0,0,+Q97/O97-1) -> 0 | S97: 88
A98: =$B$94&"."&B98 -> 11.11.4 | B98: 11.4 | C98: PROTEÇÃO DE PISO COM SALVA PISO E LONA PRETA REFORÇADA | D98: m2 | E98: 1000 | F98: 7.56 | G98: 1.2 | H98: =G98+F98 -> 8.76 | I98: =E98*G98 -> 1200 | L98: =E98*F98 -> 7560 | O98: =L98+I98 -> 8760 | Q98: =IF(K98="",I98,J98/K98)+IF(N98="",L98,M98/N98) -> 8760 | R98: =IF(O98=0,0,+Q98/O98-1) -> 0 | S98: 89
A99: =$B$94&"."&B99 -> 11.11.5 | B99: 11.5 | C99: ALUGUEL DE ANDAIMES | D99: mês | E99: 14 | F99: 1956 | H99: =G99+F99 -> 1956 | I99: =E99*G99 -> 0 | L99: =E99*F99 -> 27384 | O99: =L99+I99 -> 27384 | Q99: =IF(K99="",I99,J99/K99)+IF(N99="",L99,M99/N99) -> 27384 | R99: =IF(O99=0,0,+Q99/O99-1) -> 0 | S99: 90
A100: =$B$94&"."&B100 -> 11.11.6 | B100: 11.6 | C100: ALUGUEL DE EQUIPAMENTOS | D100: vb | E100: 1 | F100: =14000+2500 -> 16500 | H100: =G100+F100 -> 16500 | I100: =E100*G100 -> 0 | L100: =E100*F100 -> 16500 | O100: =L100+I100 -> 16500 | Q100: =IF(K100="",I100,J100/K100)+IF(N100="",L100,M100/N100) -> 16500 | R100: =IF(O100=0,0,+Q100/O100-1) -> 0 | S100: 91
A101: =$B$94&"."&B101 -> 11.11.7 | B101: 11.7 | C101: TRANSPORTE HORIZONTAL DE MATERIAIS | D101: vb | E101: 1 | F101: 4000 | H101: =G101+F101 -> 4000 | I101: =E101*G101 -> 0 | L101: =E101*F101 -> 4000 | O101: =L101+I101 -> 4000 | Q101: =IF(K101="",I101,J101/K101)+IF(N101="",L101,M101/N101) -> 4000 | R101: =IF(O101=0,0,+Q101/O101-1) -> 0 | S101: 92
A102: =$B$94&"."&B102 -> 11.11.8 | B102: 11.8 | C102: FRETES DIVERSOS | D102: vb | E102: 1 | F102: 10000 | H102: =G102+F102 -> 10000 | I102: =E102*G102 -> 0 | L102: =E102*F102 -> 10000 | O102: =L102+I102 -> 10000 | Q102: =IF(K102="",I102,J102/K102)+IF(N102="",L102,M102/N102) -> 10000 | R102: =IF(O102=0,0,+Q102/O102-1) -> 0 | S102: 93
A103: =$B$94&"."&B103 -> 11.11.9 | B103: 11.9 | C103: SISTEMA DE EXAUSTÃO PARA CHURASQUEIRA
...

Sheet BASE APURAÇÃO
A1: ='BASE OFICIAL'!B7 -> ITEM | B1: ='BASE OFICIAL'!C7 -> DESCRICAO | C1: ='BASE OFICIAL'!D7 -> UND | D1: ='BASE OFICIAL'!E7 -> QTD | E1: ='BASE OFICIAL'!F7 -> MATERIAIS | F1: ='BASE OFICIAL'!G7 -> MÃO DE OBRA | G1: ='BASE OFICIAL'!H7 -> ORÇAMENTO UNIT | H1: GERAL ORÇADO MAO DE OBRA | I1: GERAL REALIZADO MAO DE OBRA | J1: ='BASE OFICIAL'!K7 -> % | K1: GERAL ORÇADO MATERIAIS | L1: GERAL REALIZADO MATERIAIS | M1: ='BASE OFICIAL'!N7 -> % | N1: ='BASE OFICIAL'!O7 -> ORÇAMENTO TOTAL | O1: ='BASE OFICIAL'!P7 -> SALDO | P1: 1 ORÇADO MAT | Q1: 1 ORÇADO MAO | R1: 1. ORÇADO TOTAL | S1: 1 REALIZADO MAT | T1: 1 REALIADO MAO | U1: 2 ORÇADO MAT | V1: 2 ORÇADO MAO | W1: 2 REALIZADO MAT | X1: 2 REALIZADO MAO | Y1: 5 ORÇADO MAT | Z1: 5 ORÇADO MAO | AA1: 5 REALIZADO MAT | AB1: 5 REALIZADO MAO | AC1: 4 ORÇADO MAT | AD1: 4 ORÇADO MAO | AE1: 4 REALIZADO MAT | AF1: 4 REALIZADO MAO | AG1: 5 ORÇADO MAT | AH1: 5 ORÇADO MAO | AI1: 5 REALIZADO MAT | AJ1: 5 REALIZADO MAO | AK1: 6 ORÇADO MAT | AL1: 6 ORÇADO MAO | AM1: 6 REALIZADO MAT | AN1: 6 REALIZADO MAO | AO1: 7.1 ORÇADO MAT | AP1: 7.1 ORÇADO MAO | AQ1: 7.1 REALIZADO MAT | AR1: 7.1 REALIZADO MAO | AS1: 7.2 ORÇADO MAT | AT1: 7.2 ORÇADO MAO | AU1: 7.2 REALIZADO MAT | AV1: 7.2 REALIZADO MAO | AW1: 8 ORÇADO MAT | AX1: 8 ORÇADO MAO | AY1: 8 REALIZADO MAT | AZ1: 8 REALIZADO MAO | BA1: 9 ORÇADO MAT | BB1: 9 ORÇADO MAO | BC1: 9 REALIZADO MAT | BD1: 9 REALIZADO MAO | BE1: 10 ORÇADO MAT | BF1: 10 ORÇADO MATO | BG1: 10 REALIZADO MAT | BH1: 10 REALIZADO MAO | BI1: 11 ORÇADO MAT | BJ1: 11 ORÇADO MATO | BK1: 11 REALIZADO MAT | BL1: 11 REALIZADO MAO | BM1: 12 ORÇADO MAT | BN1: 12 ORÇADO MATO | BO1: 12 REALIZADO MAT | BP1: 12 REALIZADO MAO | BQ1: 13 ORÇADO MAT | BR1: 13 ORÇADO MATO | BS1: 13 REALIZADO MAT | BT1: 13 REALIZADO MAO | BU1: 14 ORÇADO MAT | BV1: 14 ORÇADO MATO | BW1: 14 REALIZADO MAT | BX1: 14 REALIZADO MAO | BY1: IGNORAR1 | BZ1: IGNORAR2 | CD1: SOMA SOLICITAÇOES
A2: ='BASE OFICIAL'!B9 -> 1 | B2: ='BASE OFICIAL'!C9 -> SERVIÇOS PRELIMINARES | C2: ='BASE OFICIAL'!D9 -> 0 | D2: ='BASE OFICIAL'!E9 -> 1681.4 | E2: ='BASE OFICIAL'!F9 -> 7357.18 | F2: ='BASE OFICIAL'!G9 -> 6798.47 | G2: ='BASE OFICIAL'!H9 -> 58643.174 | H2: ='BASE OFICIAL'!I9 -> 35228.244 | ... O2: ='BASE OFICIAL'!P9 -> 0 | P2: =$K2 -> 58643.174 | Q2: =$H2 -> 35228.244 | R2: =P2+Q2 -> 93871.418 | S2: =$L2 -> 0 | T2: =$I2 -> 0 | U2: =$K5 -> 65432.829 | V2: =$H5 -> 107742.46 | W2: =$L5 -> 0 | X2: =$I5 -> 0 | Y2: =$K4 -> 199902.18 | Z2: =$H4 -> 103630.63 | AA2: =$L4 -> 0 | AB2: =$I4 -> 0 | AC2: =$K5 -> 65432.829 | AD2: =$H5 -> 107742.46 | AE2: =$L5 -> 0 | AF2: =$I5 -> 0 | AG2: =$K6 -> 76914 | AH2: =$H6 -> 183374.26 | AI2: =$L6 -> 0 | AJ2: =$I6 -> 0 | AK2: =$K7 -> 16735.741 | AL2: =$H7 -> 66796.81 | AM2: =$L7 -> 0 | AN2: =$I7 -> 0 | AO2: =$K8 -> 25794.013 | AP2: =$H8 -> 98538.747 | AQ2: =$L8 -> 0 | AR2: =$I8 -> 0 | AS2: =$K9 -> 712.32 | AT2: =$H9 -> 1413.75 | AU2: =$L9 -> 0 | AV2: =$I9 -> 0 | AW2: =$K10 -> 1959.75 | AX2: =$H10 -> 13879.35 | AY2: =$L10 -> 0 | AZ2: =$I10 -> 0 | BA2: =$K11 -> 956 | BB2: =$H11 -> 4339 | BC2: =$L11 -> 0 | BD2: =$I11 -> 0 | BE2: =$K12 -> 48922.23 | BF2: =$H12 -> 42479.171 | BG2: =$L12 -> 0 | BH2: =$I12 -> 0 | BI2: =$K13 -> 109457.06 | BJ2: =$H13 -> 74168.864 | BK2: =$L13 -> 0 | BL2: =$I13 -> 0 | BM2: =$K14 -> 93910.5 | BN2: =$H14 -> 16024 | BO2: =$L14 -> 0 | BP2: =$I14 -> 0 | BQ2: =$K15 -> 134094 | BR2: =$H15 -> 71105 | BS2: =$L15 -> 0 | BT2: =$I15 -> 0 | BU2: =$K16 -> 0 | BV2: =$H16 -> 78400 | BW2: =$L16 -> 0 | BX2: =$I16 -> 0 | CD2: =SUM(CA:CA) -> 0
A3: ='BASE OFICIAL'!B19 -> 2 | B3: ='BASE OFICIAL'!C19 -> FUNDAÇÕES EM SAPATAS, LAJE DE PISO | C3: ='BASE OFICIAL'!D19 -> 0 | D3: ='BASE OFICIAL'!E19 -> 4111.74 | E3: ='BASE OFICIAL'!F19 -> 0 | F3: ='BASE OFICIAL'!G19 -> 0 | G3: ='BASE OFICIAL'!H19 -> 185580.7 | H3: ='BASE OFICIAL'!I19 -> 176404.95 | ... O3: ='BASE OFICIAL'!P19 -> 0
A4: ='BASE OFICIAL'!B34 -> 3 | B4: ='BASE OFICIAL'!C34 -> SUPRA ESTRUTURA (ESTIMATIVA SEM PROJETO) | C4: ='BASE OFICIAL'!D34 -> vb | D4: ='BASE OFICIAL'!E34 -> 1 | E4: ='BASE OFICIAL'!F34 -> 8569 | F4: ='BASE OFICIAL'!G34 -> 4859 | G4: ='BASE OFICIAL'!H34 -> 8569 | H4: ='BASE OFICIAL'!I34 -> 103630.63 | ... O4: ='BASE OFICIAL'!P34 -> 0
A5: ='BASE OFICIAL'!B41 -> 4 | B5: ='BASE OFICIAL'!C41 -> ALVENARIAS E FECHAMENTOS | C5: ='BASE OFICIAL'!D41 -> 0 | D5: ='BASE OFICIAL'!E41 -> 3663.11 | E5: ='BASE OFICIAL'!F41 -> 0 | F5: ='BASE OFICIAL'!G41 -> 0 | G5: ='BASE OFICIAL'!H41 -> 42488.34 | H5: ='BASE OFICIAL'!I41 -> 107742.46 | ... O5: ='BASE OFICIAL'!P41 -> 0
A6: ='BASE OFICIAL'!B52 -> 5.1 | B6: ='BASE OFICIAL'!C52 -> REVESTIMENTOS PAREDE | C6: ='BASE OFICIAL'!D52 -> 0 | D6: ='BASE OFICIAL'!E52 -> 10130.57 | E6: ='BASE OFICIAL'!F52 -> 0 | F6: ='BASE OFICIAL'!G52 -> 0 | G6: ='BASE OFICIAL'!H52 -> 308.22 | H6: ='BASE OFICIAL'!I52 -> 183374.26 | ... O6: ='BASE OFICIAL'!P52 -> 0
A7: ='BASE OFICIAL'!B59 -> 5.2 | B7: ='BASE OFICIAL'!C59 -> REVESTIMENTOS TETO | C7: ='BASE OFICIAL'!D59 -> 0 | D7: ='BASE OFICIAL'!E59 -> 1205.0125 | E7: ='BASE OFICIAL'!F59 -> 0 | F7: ='BASE OFICIAL'!G59 -> 0 | G7: ='BASE OFICIAL'!H59 -> 3270.79 | H7: ='BASE OFICIAL'!I59 -> 66796.81 | ... O7: ='BASE OFICIAL'!P59 -> 0
A8: ='BASE OFICIAL'!B65 -> 6 | B8: ='BASE OFICIAL'!C65 -> PAVIMENTAÇÃO | C8: ='BASE OFICIAL'!D65 -> 0 | D8: ='BASE OFICIAL'!E65 -> 3086.39 | E8: ='BASE OFICIAL'!F65 -> 0 | F8: ='BASE OFICIAL'!G65 -> 0 | G8: ='BASE OFICIAL'!H65 -> 417.88 | H8: ='BASE OFICIAL'!I65 -> 98538.747 | ... O8: ='BASE OFICIAL'!P65 -> 0
A9: ='BASE OFICIAL'!B74 -> 7.1 | B9: ='BASE OFICIAL'!C74 -> FILETE DE BOX E SOLEIRA | C9: ='BASE OFICIAL'!D74 -> 0 | D9: ='BASE OFICIAL'!E74 -> 42.26 | E9: ='BASE OFICIAL'!F74 -> 0 | F9: ='BASE OFICIAL'!G74 -> 0 | G9: ='BASE OFICIAL'!H74 -> 101 | H9: ='BASE OFICIAL'!I74 -> 1413.75 | ... O9: ='BASE OFICIAL'!P74 -> 0
A10: ='BASE OFICIAL'!B77 -> 7.2 | B10: ='BASE OFICIAL'!C77 -> BANCADA | C10: ='BASE OFICIAL'!D77 -> 0 | D10: ='BASE OFICIAL'!E77 -> 86.39 | E10: ='BASE OFICIAL'!F77 -> 0 | F10: ='BASE OFICIAL'!G77 -> 0 | G10: ='BASE OFICIAL'!H77 -> 325 | H10: ='BASE OFICIAL'!I77 -> 13879.35 | ... O10: ='BASE OFICIAL'!P77 -> 0
A11: ='BASE OFICIAL'!B81 -> 8 | B11: ='BASE OFICIAL'!C81 -> LOUÇAS E METAIS | C11: ='BASE OFICIAL'!D81 -> 0 | D11: ='BASE OFICIAL'!E81 -> 3 | E11: ='BASE OFICIAL'!F81 -> 0 | F11: ='BASE OFICIAL'!G81 -> 0 | G11: ='BASE OFICIAL'!H81 -> 3606 | H11: ='BASE OFICIAL'!I81 -> 4339 | ... O11: ='BASE OFICIAL'!P81 -> 0
A12: ='BASE OFICIAL'!B85 -> 9 | B12: ='BASE OFICIAL'!C85 -> PINTURA | C12: ='BASE OFICIAL'!D85 -> 0 | D12: ='BASE OFICIAL'!E85 -> 1308.1655 | E12: ='BASE OFICIAL'!F85 -> 0 | F12: ='BASE OFICIAL'!G85 -> 0 | G12: ='BASE OFICIAL'!H85 -> 287.54 | H12: ='BASE OFICIAL'!I85 -> 42479.171 | ... O12: ='BASE OFICIAL'!P85 -> 0
A13: ='BASE OFICIAL'!B90 -> 10 | B13: ='BASE OFICIAL'!C90 -> COBERTURA | C13: ='BASE OFICIAL'!D90 -> 0 | D13: ='BASE OFICIAL'!E90 -> 835.548 | E13: ='BASE OFICIAL'!F90 -> 0 | F13: ='BASE OFICIAL'!G90 -> 0 | G13: ='BASE OFICIAL'!H90 -> 728.56 | H13: ='BASE OFICIAL'!I90 -> 74168.864 | ... O13: ='BASE OFICIAL'!P90 -> 0
A14: ='BASE OFICIAL'!B94 -> 11 | B14: ='BASE OFICIAL'!C94 -> LIMPEZA E DIVERSOS | C14: ='BASE OFICIAL'!D94 -> 0 | D14: ='BASE OFICIAL'!E94 -> 1036 | E14: ='BASE OFICIAL'!F94 -> 0 | F14: ='BASE OFICIAL'!G94 -> 0 | G14: ='BASE OFICIAL'!H94 -> 66815.51 | H14: ='BASE OFICIAL'!I94 -> 16024 | ... O14: ='BASE OFICIAL'!P94 -> 0
A15: ='BASE OFICIAL'!B108 -> 12 | B15: ='BASE OFICIAL'!C108 -> INSTALAÇÕES - ESTIMATIVA SEM PROJETO | C15: ='BASE OFICIAL'!D108 -> 0 | D15: ='BASE OFICIAL'!E108 -> 27 | E15: ='BASE OFICIAL'!F108 -> 0 | F15: ='BASE OFICIAL'!G108 -> 0 | G15: ='BASE OFICIAL'!H108 -> 202634 | H15: ='BASE OFICIAL'!I108 -> 71105 | ... O15: ='BASE OFICIAL'!P108 -> 0
A16: ='BASE OFICIAL'!B121 -> 13 | B16: ='BASE OFICIAL'!C121 -> MÃO DE OBRA DE APOIO | C16: ='BASE OFICIAL'!D121 -> 0 | D16: ='BASE OFICIAL'!E121 -> 42 | E16: ='BASE OFICIAL'!F121 -> 0 | F16: ='BASE OFICIAL'!G121 -> 0 | G16: ='BASE OFICIAL'!H121 -> 5600 | H16: ='BASE OFICIAL'!I121 -> 78400 | ... O16: ='BASE OFICIAL'!P121 -> 0
A17: ='BASE OFICIAL'!B125 -> 14 | B17: ='BASE OFICIAL'!C125 -> PISCINA | C17: ='BASE OFICIAL'!D125 -> 0 | D17: ='BASE OFICIAL'!E125 -> 1936.1195 | E17: ='BASE OFICIAL'!F125 -> 0 | F17: ='BASE OFICIAL'!G125 -> 0 | G17: ='BASE OFICIAL'!H125 -> 25079.85 | H17: ='BASE OFICIAL'!I125 -> 52231.096 | ... O17: ='BASE OFICIAL'!P125 -> 0

Sheet DADOS PAGAMENTOS
A1: VALOR | B1: MÊS | C1: SOLICITAÇÃO | D1: MAO DE OBRA | E1: MATERIAL
A2: ='BASE OFICIAL'!Q174 -> 36227.68 | B2: ='BASE OFICIAL'!R174 -> 45576 | C2: ='BASE OFICIAL'!P174 -> 1 | D2: =SUMIF(#REF!,"1",#REF!) -> #REF! | E2: =SUMIF(#REF!,1,#REF!) -> #REF!
A3: ='BASE OFICIAL'!Q175 -> 58915.23 | B3: ='BASE OFICIAL'!R175 -> 45688 | C3: ='BASE OFICIAL'!P175 -> 2 | D3: =SUMIF(#REF!,"2",#REF!) -> #REF! | E3: =SUMIF(#REF!,2,#REF!) -> #REF!
A4: ='BASE OFICIAL'!Q176 -> 47960.25 | B4: ='BASE OFICIAL'!R176 -> 45702 | C4: ='BASE OFICIAL'!P176 -> 3 | D4: =SUMIF(#REF!,"3",#REF!) -> #REF! | E4: =SUMIF(#REF!,3,#REF!) -> #REF!
A5: ='BASE OFICIAL'!Q177 -> 73496.82 | B5: ='BASE OFICIAL'!R177 -> FEVEREIRO | C5: ='BASE OFICIAL'!P177 -> 4 | D5: =SUMIF(#REF!,"4",#REF!) -> #REF! | E5: =SUMIF(#REF!,4,#REF!) -> #REF!
A6: ='BASE OFICIAL'!Q178 -> 0 | B6: ='BASE OFICIAL'!R178 -> 0 | C6: ='BASE OFICIAL'!P178 -> 0
A7: ='BASE OFICIAL'!Q179 -> 0 | B7: ='BASE OFICIAL'!R179 -> 0 | C7: ='BASE OFICIAL'!P179 -> 0
A8: ='BASE OFICIAL'!Q180 -> 0 | B8: ='BASE OFICIAL'!R180 -> 0 | C8: ='BASE OFICIAL'!P180 -> 0
A9: ='BASE OFICIAL'!Q181 -> 0 | B9: ='BASE OFICIAL'!R181 -> 0 | C9: ='BASE OFICIAL'!P181 -> 0
A10: ='BASE OFICIAL'!Q182 -> 0 | B10: ='BASE OFICIAL'!R182 -> 0 | C10: ='BASE OFICIAL'!P182 -> 0
A11: ='BASE OFICIAL'!Q183 -> 0 | B11: ='BASE OFICIAL'!R183 -> 0 | C11: ='BASE OFICIAL'!P183 -> 0
A12: ='BASE OFICIAL'!Q184 -> 0 | B12: ='BASE OFICIAL'!R184 -> 0 | C12: ='BASE OFICIAL'!P184 -> 0
A13: ='BASE OFICIAL'!Q185 -> 0 | B13: ='BASE OFICIAL'!R185 -> 0 | C13: ='BASE OFICIAL'!P185 -> 0
A14: ='BASE OFICIAL'!Q186 -> 0 | B14: ='BASE OFICIAL'!R186 -> 0 | C14: ='BASE OFICIAL'!P186 -> 0
A15: ='BASE OFICIAL'!Q187 -> 0 | B15: ='BASE OFICIAL'!R187 -> 0 | C15: ='BASE OFICIAL'!P187 -> 0
A16: ='BASE OFICIAL'!Q188 -> 0 | B16: ='BASE OFICIAL'!R188 -> 0 | C16: ='BASE OFICIAL'!P188 -> 0
A17: ='BASE OFICIAL'!Q189 -> 0 | B17: ='BASE OFICIAL'!R189 -> 0 | C17: ='BASE OFICIAL'!P189 -> 0
... A19: ='BASE OFICIAL'!Q191 -> 0 | B19: ='BASE OFICIAL'!R191 -> 0 | C19: ='BASE OFICIAL'!P191 -> 0

Sheet Planilha2
A1: PLACA DE OBRA EM CHAPA DE ACO GALVANIZADO | B1: =COUNTIF(A1:A127,A1) -> 1
A2: BARRACAO DE OBRA ALOJAMENTO/ESCRITORIO. | B2: =COUNTIF(A2:A128,A2) -> 1
A3: EQUIPAMENTOS PARA BARRACÃO | B3: =COUNTIF(A3:A129,A3) -> 1
A4: LIMPEZA MANUAL DE VEGETAÇÃO EM TERRENO. | B4: =COUNTIF(A4:A130,A4) -> 1
A5: LOCACAO CONVENCIONAL DE OBRA (GABARITO) | B5: =COUNTIF(A5:A131,A5) -> 1
A6: MOVIMENTAÇÃO DE TERRA | B6: =COUNTIF(A6:A132,A6) -> 1
A7: TAPUME COM TELHA METÁLICA. | B7: =COUNTIF(A7:A133,A7) -> 1
A8: INSTALAÇÃO PROVISÓRIA ELÉTRICA E HIDRÁULICA | B8: =COUNTIF(A8:A134,A8) -> 1
A9: FUNDAÇÕES EM SAPATAS, LAJE DE PISO | B9: =COUNTIF(A9:A135,A9) -> 1
A10: ESCAVAÇÃO MANUAL DE VALA EM SOLO DE 1ª CATEGORIA, PROFUNDIDADE ENTRE 1,5 E 4,0 M | B10: =COUNTIF(A10:A136,A10) -> 1
A11: APILOAMENTO DE FUNDO DE VALAS | B11: =COUNTIF(A11:A137,A11) -> 1
A12: CONCRETO MAGRO, CONFECÇÃO E LANÇAMENTO (FCK=6MPA) | B12: =COUNTIF(A12:A138,A12) -> 1
... A127: EQUIPAMENTOS PARA PISCINA (P) - SEM ILUMINAÇÃO | B127: =COUNTIF(A127:A253,A127) -> 1
